MatrixTest/MatrixTestRunner.py
MatrixTest/Printers.py
MatrixTest/Utils.py
MatrixTest/__init__.py
MatrixTest/EmailService/EmailProvider.py
MatrixTest/EmailService/MailjetProvider.py
MatrixTest/EmailService/__init__.py
MatrixTest-1.3.0.dist-info/LICENSE
MatrixTest-1.3.0.dist-info/METADATA
MatrixTest-1.3.0.dist-info/WHEEL
MatrixTest-1.3.0.dist-info/top_level.txt
MatrixTest-1.3.0.dist-info/RECORD
