Metadata-Version: 2.1
Name: MatrixTest
Version: 1.3.0
Summary: A tool to facilitate matrix test via countless combination of arguments of a command line
Home-page: https://github.com/DavyVan/MatrixTest
Author: Quan Fan
Author-email: qfan005@ucr.edu
License: UNKNOWN
Project-URL: Bug Tracker, https://github.com/DavyVan/MatrixTest/issues
Platform: UNKNOWN
Classifier: Programming Language :: Python :: 3
Classifier: Programming Language :: Python :: 3.7
Classifier: Programming Language :: Python :: 3.8
Classifier: Programming Language :: Python :: 3.9
Classifier: License :: OSI Approved :: MIT License
Classifier: Operating System :: OS Independent
Classifier: Topic :: Software Development :: Libraries :: Python Modules
Classifier: Topic :: Software Development :: Quality Assurance
Classifier: Topic :: Software Development :: Testing
Classifier: Topic :: System :: Benchmark
Classifier: Topic :: System :: Shells
Classifier: Topic :: System :: System Shells
Classifier: Topic :: Utilities
Classifier: Environment :: Console
Classifier: Intended Audience :: Developers
Classifier: Intended Audience :: Science/Research
Requires-Python: >=3.7.1
Requires-Dist: pandas
Requires-Dist: colorama
Requires-Dist: openpyxl
Requires-Dist: mailjet-rest
